{"version":3,"kind":"Notebook","sha256":"baaa105077dfa91b0c6c251d766ce9a0fff0d0c4a1dffa42b7040cf74ce70245","slug":"notebooks.geopandas-visualization","location":"/notebooks/Geopandas_Visualization.ipynb","dependencies":[],"frontmatter":{"title":"METAR GeoParquet Interactive Visualization","authors":[{"id":"ktyle","nameParsed":{"literal":"Kevin Tyle","given":"Kevin","family":"Tyle"},"name":"Kevin Tyle","orcid":"0000-0001-5249-9665","affiliations":["UAlbany"],"github":"ktyle"}],"content_includes_title":false,"kernelspec":{"name":"python3","display_name":"Python 3 (ipykernel)","language":"python"},"open_access":true,"license":{"content":{"id":"CC-BY-4.0","url":"https://creativecommons.org/licenses/by/4.0/","name":"Creative Commons Attribution 4.0 International","free":true,"CC":true},"code":{"id":"Apache-2.0","url":"https://opensource.org/licenses/Apache-2.0","name":"Apache License 2.0","free":true,"osi":true}},"github":"https://github.com/projectpythia/Metar_archive-cookbook","copyright":"2026","affiliations":[{"id":"UAlbany","name":"University at Albany (SUNY)","department":"Atmospheric and Environmental Sciences","url":"https://www.albany.edu/daes"},{"id":"CISL","name":"NSF National Center for Atmospheric Research","department":"Computational and Information Systems Lab","url":"https://www.cisl.ucar.edu"},{"id":"Unidata","name":"NSF Unidata","url":"https://www.unidata.ucar.edu"},{"id":"Argonne","name":"Argonne National Laboratory","department":"Environmental Science Division","url":"https://www.anl.gov/evs"},{"id":"CarbonPlan","name":"CarbonPlan","url":"https://carbonplan.org"},{"id":"NVIDIA","name":"NVIDIA Corporation","url":"https://www.nvidia.com/"},{"id":"University at Albany (State University of New York)","name":"University at Albany (State University of New York)"},{"id":"UCAR | UCP | NSF Unidata","name":"UCAR | UCP | NSF Unidata"},{"id":"CIRES University of Colorado Boulder","name":"CIRES University of Colorado Boulder"},{"id":"Colorado State University","name":"Colorado State University"},{"id":"Boise State University","name":"Boise State University"},{"id":"Montclair State University","name":"Montclair State University"},{"id":"NSF NCAR EOL","name":"NSF NCAR EOL"}],"numbering":{"title":{"offset":1}},"source_url":"https://github.com/projectpythia/Metar_archive-cookbook/blob/main/notebooks/Geopandas_Visualization.ipynb","edit_url":"https://github.com/projectpythia/Metar_archive-cookbook/edit/main/notebooks/Geopandas_Visualization.ipynb","exports":[{"format":"ipynb","filename":"Geopandas_Visualization.ipynb","url":"/METAR_archive-cookbook/build/Geopandas_Visualizat-bdc85059ea7cfbf53c3ca1cd1b7dbdca.ipynb"}]},"widgets":{},"mdast":{"type":"root","children":[{"type":"block","kind":"notebook-content","children":[{"type":"heading","depth":2,"position":{"start":{"line":1,"column":1},"end":{"line":1,"column":1}},"children":[{"type":"text","value":"Overview","position":{"start":{"line":1,"column":1},"end":{"line":1,"column":1}},"key":"UX6qBfIDyJ"}],"identifier":"overview","label":"Overview","html_id":"overview","implicit":true,"key":"b58aHvZXAK"},{"type":"paragraph","position":{"start":{"line":3,"column":1},"end":{"line":3,"column":1}},"children":[{"type":"text","value":"Within this notebook, we will create interactive visualizations of METAR data at a single hour. We will use the following libraries for our visualizations:","position":{"start":{"line":3,"column":1},"end":{"line":3,"column":1}},"key":"EYhfMC76dG"}],"key":"MThbWBQOTS"},{"type":"list","ordered":true,"start":1,"spread":false,"position":{"start":{"line":5,"column":1},"end":{"line":6,"column":1}},"children":[{"type":"listItem","spread":true,"position":{"start":{"line":5,"column":1},"end":{"line":6,"column":1}},"children":[{"type":"paragraph","children":[{"type":"link","url":"https://geopandas.org/en/stable/","position":{"start":{"line":5,"column":1},"end":{"line":5,"column":1}},"children":[{"type":"text","value":"Geopandas","position":{"start":{"line":5,"column":1},"end":{"line":5,"column":1}},"key":"sOkVYD3w0r"}],"urlSource":"https://geopandas.org/en/stable/","key":"GRW1auZXI7"}],"key":"CILFGO9lgH"}],"key":"gWCFo3Yq3k"}],"key":"yCxiYE40UQ"},{"type":"heading","depth":2,"position":{"start":{"line":7,"column":1},"end":{"line":7,"column":1}},"children":[{"type":"text","value":"Prerequisites","position":{"start":{"line":7,"column":1},"end":{"line":7,"column":1}},"key":"ZvXehtHo8i"}],"identifier":"prerequisites","label":"Prerequisites","html_id":"prerequisites","implicit":true,"key":"uopL58xiCC"},{"type":"table","position":{"start":{"line":8,"column":1},"end":{"line":11,"column":1}},"children":[{"type":"tableRow","position":{"start":{"line":8,"column":1},"end":{"line":8,"column":1}},"children":[{"type":"tableCell","header":true,"position":{"start":{"line":8,"column":1},"end":{"line":8,"column":1}},"children":[{"type":"text","value":"Concepts","position":{"start":{"line":8,"column":1},"end":{"line":8,"column":1}},"key":"EdhGDSE3kY"}],"key":"qdL7CWWipO"},{"type":"tableCell","header":true,"position":{"start":{"line":8,"column":1},"end":{"line":8,"column":1}},"children":[{"type":"text","value":"Importance","position":{"start":{"line":8,"column":1},"end":{"line":8,"column":1}},"key":"Jy3JCswVL3"}],"key":"IZcBH2Jbs2"},{"type":"tableCell","header":true,"position":{"start":{"line":8,"column":1},"end":{"line":8,"column":1}},"children":[{"type":"text","value":"Notes","position":{"start":{"line":8,"column":1},"end":{"line":8,"column":1}},"key":"fcaliXQXO8"}],"key":"i2W0UdfPOx"}],"key":"lPBY0np8Dv"},{"type":"tableRow","position":{"start":{"line":10,"column":1},"end":{"line":10,"column":1}},"children":[{"type":"tableCell","position":{"start":{"line":10,"column":1},"end":{"line":10,"column":1}},"children":[{"type":"link","url":"https://foundations.projectpythia.org/core/cartopy/cartopy.html","position":{"start":{"line":10,"column":1},"end":{"line":10,"column":1}},"children":[{"type":"text","value":"Cartopy Intro","position":{"start":{"line":10,"column":1},"end":{"line":10,"column":1}},"key":"PLwy96rmvS"}],"urlSource":"https://foundations.projectpythia.org/core/cartopy/cartopy.html","key":"T7ha3FBjqm"}],"key":"v529INjiJ4"},{"type":"tableCell","position":{"start":{"line":10,"column":1},"end":{"line":10,"column":1}},"children":[{"type":"text","value":"Required","position":{"start":{"line":10,"column":1},"end":{"line":10,"column":1}},"key":"ybVpuKjivO"}],"key":"eIEwl0eIrV"},{"type":"tableCell","position":{"start":{"line":10,"column":1},"end":{"line":10,"column":1}},"children":[{"type":"text","value":"Projections and Features","position":{"start":{"line":10,"column":1},"end":{"line":10,"column":1}},"key":"pTYPn7LnLP"}],"key":"MmOrGYNC2R"}],"key":"HMjnAZ1exL"},{"type":"tableRow","position":{"start":{"line":11,"column":1},"end":{"line":11,"column":1}},"children":[{"type":"tableCell","position":{"start":{"line":11,"column":1},"end":{"line":11,"column":1}},"children":[{"type":"link","url":"https://foundations.projectpythia.org/core/pandas.html","position":{"start":{"line":11,"column":1},"end":{"line":11,"column":1}},"children":[{"type":"text","value":"Pandas","position":{"start":{"line":11,"column":1},"end":{"line":11,"column":1}},"key":"XhmGnNhX8J"}],"urlSource":"https://foundations.projectpythia.org/core/pandas.html","key":"hQre67kAd7"}],"key":"wzmit9QX3o"},{"type":"tableCell","position":{"start":{"line":11,"column":1},"end":{"line":11,"column":1}},"children":[{"type":"text","value":"Required","position":{"start":{"line":11,"column":1},"end":{"line":11,"column":1}},"key":"VGEr1jnvpP"}],"key":"OxitDoaXO9"},{"type":"tableCell","position":{"start":{"line":11,"column":1},"end":{"line":11,"column":1}},"children":[{"type":"text","value":"Tabular Datasets","position":{"start":{"line":11,"column":1},"end":{"line":11,"column":1}},"key":"ZTVxCHue7z"}],"key":"OrJ6b3u6Tb"}],"key":"J2NObsYpyB"}],"key":"LijnJ51Hwt"},{"type":"list","ordered":false,"spread":false,"position":{"start":{"line":13,"column":1},"end":{"line":13,"column":1}},"children":[{"type":"listItem","spread":true,"position":{"start":{"line":13,"column":1},"end":{"line":13,"column":1}},"children":[{"type":"paragraph","children":[{"type":"strong","position":{"start":{"line":13,"column":1},"end":{"line":13,"column":1}},"children":[{"type":"text","value":"Time to learn","position":{"start":{"line":13,"column":1},"end":{"line":13,"column":1}},"key":"TtAG4ckdPK"}],"key":"mb21UgAy70"},{"type":"text","value":": 20 minutes","position":{"start":{"line":13,"column":1},"end":{"line":13,"column":1}},"key":"A2949z0E99"}],"key":"TfJNUFWWxY"}],"key":"QUaQUiK7j9"}],"key":"OBMhN66ISz"},{"type":"thematicBreak","position":{"start":{"line":14,"column":1},"end":{"line":14,"column":1}},"key":"A3sxGLPSV1"}],"key":"LYuDVcf71L"},{"type":"block","kind":"notebook-content","data":{"tags":[]},"children":[{"type":"heading","depth":2,"position":{"start":{"line":1,"column":1},"end":{"line":1,"column":1}},"children":[{"type":"text","value":"Imports","position":{"start":{"line":1,"column":1},"end":{"line":1,"column":1}},"key":"aH7HgEL1Qs"}],"identifier":"imports","label":"Imports","html_id":"imports","implicit":true,"key":"OAY0fKIdaV"}],"visibility":"show","key":"hmcwoZDuVl"},{"type":"block","kind":"notebook-code","children":[{"type":"code","lang":"python","executable":true,"value":"import matplotlib.pyplot as plt\nimport pandas as pd\nimport numpy as np\nfrom datetime import datetime,timedelta\nimport geopandas as gpd\nfrom lonboard import viz, Map, ScatterplotLayer, HeatmapLayer\nimport duckdb\nimport folium","key":"Wovb46lQHH"},{"type":"outputs","id":"AtlYE_7fqh3DkmxVHdPy-","children":[],"key":"zolOjrkyZj"}],"key":"lEfCiNZ8Ye"},{"type":"block","kind":"notebook-content","children":[{"type":"heading","depth":3,"position":{"start":{"line":1,"column":1},"end":{"line":1,"column":1}},"children":[{"type":"text","value":"By default, set the date and time to one hour prior to the current time. Or, specify a past date and hour.","position":{"start":{"line":1,"column":1},"end":{"line":1,"column":1}},"key":"UXcyElge4l"}],"identifier":"by-default-set-the-date-and-time-to-one-hour-prior-to-the-current-time-or-specify-a-past-date-and-hour","label":"By default, set the date and time to one hour prior to the current time. Or, specify a past date and hour.","html_id":"by-default-set-the-date-and-time-to-one-hour-prior-to-the-current-time-or-specify-a-past-date-and-hour","implicit":true,"key":"LL4RzYEdZF"}],"key":"zqseOGi4Aj"},{"type":"block","kind":"notebook-code","children":[{"type":"code","lang":"python","executable":true,"value":"# Use the current time, or set your own for a past time.\n# Set current to False if you want to specify a past time.\n\nnowTime = datetime.now()\n\ncurrent = True\n#current = False\nif (current):\n    time_1 = datetime.now()\n    offset = timedelta(hours = 1) # Worldwide METARS typically don't come in until ~15 minutes past the hour\n    time_1 = time_1 - offset\nelse:\n    year = 2026\n    month = 1\n    day = 1\n    hour = 0\n    time_1 = datetime(year, month, day, hour)","key":"AhBauYcWLK"},{"type":"outputs","id":"mk-dwvPfd1Gm5MiQA-jhS","children":[],"key":"vef1wPbQEZ"}],"key":"QHEvRUxYbf"},{"type":"block","kind":"notebook-content","children":[{"type":"paragraph","position":{"start":{"line":1,"column":1},"end":{"line":1,"column":1}},"children":[{"type":"text","value":"The timestamps of many hourly METAR reports are 5-10 minutes prior to the top of the hour. When we make our DuckDB query, we will specify a beginning and end time, one hour apart.","position":{"start":{"line":1,"column":1},"end":{"line":1,"column":1}},"key":"O7FY3DEXsn"}],"key":"M42y7I6vwN"}],"key":"WhDC33tIr0"},{"type":"block","kind":"notebook-code","children":[{"type":"code","lang":"python","executable":true,"value":"time_0 = time_1 - timedelta(hours=1)\nYYYY_0 = time_0.strftime(\"%Y\")\nYYYY_1 = time_1.strftime(\"%Y\")\ndate_string = time_1.strftime(\"%Y-%m-%d %H00 UTC\")\nprint(time_0, time_1)\n# Handle edge case when the two hours straddle the end/beginning of a yearw\nif (YYYY_0 == YYYY_1):\n    URLs = [f'https://data.source.coop/dynamical/asos-parquet/year={YYYY_1}/data.parquet']\nelse:\n    URLs = [f'https://data.source.coop/dynamical/asos-parquet/year={YYYY_0}/data.parquet',\n            f'https://data.source.coop/dynamical/asos-parquet/year={YYYY_1}/data.parquet']\n","key":"AguHpPXdvj"},{"type":"outputs","id":"czIV4eKcFr4hxtH_vvXpI","children":[{"type":"output","children":[],"jupyter_data":{"output_type":"stream","name":"stdout","text":"2026-06-20 02:20:39.870215 2026-06-20 03:20:39.870215\n"},"key":"uVNSvI0KRU"}],"key":"YyoAUycLzQ"}],"key":"NQ3S0M4dvc"},{"type":"block","kind":"notebook-code","children":[{"type":"code","lang":"python","executable":true,"value":"date_string","key":"meg3zrOWIR"},{"type":"outputs","id":"erC9e7fcmw_VfaZEAOBFy","children":[{"type":"output","children":[],"jupyter_data":{"output_type":"execute_result","execution_count":4,"metadata":{},"data":{"text/plain":{"content":"'2026-06-20 0300 UTC'","content_type":"text/plain"}}},"key":"AIz5U55H7T"}],"key":"f1YTV1tiS8"}],"key":"BRK9QDRcFv"},{"type":"block","kind":"notebook-code","children":[{"type":"code","lang":"python","executable":true,"value":"URLs","key":"i9dhnyDxS8"},{"type":"outputs","id":"_FHC_HJ3usiDnzYk6pBz8","children":[{"type":"output","children":[],"jupyter_data":{"output_type":"execute_result","execution_count":5,"metadata":{},"data":{"text/plain":{"content":"['https://data.source.coop/dynamical/asos-parquet/year=2026/data.parquet']","content_type":"text/plain"}}},"key":"e2UXwFCCWu"}],"key":"uvqXAvMq9C"}],"key":"CdktYZiZ90"},{"type":"block","kind":"notebook-content","children":[{"type":"heading","depth":3,"position":{"start":{"line":1,"column":1},"end":{"line":1,"column":1}},"children":[{"type":"text","value":"Open the GeoParquet file for the specific year.","position":{"start":{"line":1,"column":1},"end":{"line":1,"column":1}},"key":"qdpBlGjTYx"}],"identifier":"open-the-geoparquet-file-for-the-specific-year","label":"Open the GeoParquet file for the specific year.","html_id":"open-the-geoparquet-file-for-the-specific-year","implicit":true,"key":"wvcfYhjF1y"}],"key":"s9LlXtnbq9"},{"type":"block","kind":"notebook-code","data":{"tags":[]},"children":[{"type":"code","lang":"python","executable":true,"value":"df = duckdb.execute(\"\"\"\n    SELECT *\n    FROM read_parquet($1, hive_partitioning=true)\n    WHERE \n---      country = 'FR' AND\n---    station = 'ENGM' AND\n    valid BETWEEN $2 AND $3\n    ORDER BY country\n\"\"\", [URLs, time_0, time_1]).fetchdf()","visibility":"show","key":"HMBh5vRn4l"},{"type":"outputs","id":"u1t5t0M8xexJko8519g8N","children":[{"type":"output","children":[],"jupyter_data":{"output_type":"display_data","metadata":{},"data":{"text/plain":{"content":"FloatProgress(value=0.0, layout=Layout(width='auto'), style=ProgressStyle(bar_color='black'))","content_type":"text/plain"},"application/vnd.jupyter.widget-view+json":{"content":"{\"version_major\":2,\"version_minor\":0,\"model_id\":\"d4c99f04b90e4fc796c33770e0e30cbb\"}","content_type":"application/vnd.jupyter.widget-view+json"}}},"key":"w7UMWRkZCh"}],"visibility":"show","key":"rviUEh0Sjq"}],"visibility":"show","key":"jMmeKbxgI4"},{"type":"block","kind":"notebook-code","children":[{"type":"code","lang":"python","executable":true,"value":"df","key":"MtFgcsfGzC"},{"type":"outputs","id":"z1Q-q_0t1FsLQAEs00kKv","children":[{"type":"output","children":[],"jupyter_data":{"output_type":"execute_result","execution_count":7,"metadata":{},"data":{"text/plain":{"content":"     station                     valid  longitude  latitude  tmpf  tmpc  dwpf  \\\n0       NZQN 2026-06-20 02:30:00+00:00   168.7392  -45.0211  51.8  11.0  50.0   \n1       NZQN 2026-06-20 03:00:00+00:00   168.7392  -45.0211  51.8  11.0  50.0   \n2       YAMB 2026-06-20 02:30:00+00:00   152.7111  -27.6297  75.2  24.0  55.4   \n3       YPPH 2026-06-20 02:30:00+00:00   115.9761  -31.9275  57.2  14.0  46.4   \n4       YBAS 2026-06-20 02:30:00+00:00   133.8890  -23.7951  57.2  14.0  44.6   \n...      ...                       ...        ...       ...   ...   ...   ...   \n6425    FAEL 2026-06-20 03:00:00+00:00    27.8259  -33.0356  53.6  12.0  48.2   \n6426    FASB 2026-06-20 02:55:00+00:00    17.8875  -29.6719  60.8  16.0  42.8   \n6427    FAUP 2026-06-20 03:00:00+00:00    21.2597  -28.4136  50.0  10.0  42.8   \n6428    FAUT 2026-06-20 03:00:00+00:00    28.6700  -31.5300  46.4   8.0  44.6   \n6429    FAWB 2026-06-20 03:00:00+00:00    28.2242  -25.6539  51.8  11.0  42.8   \n\n      dwpc   relh   drct  ...  state  \\\n0     10.0  93.55  250.0  ...     AU   \n1     10.0  93.55  250.0  ...     AU   \n2     13.0  50.22  320.0  ...     AU   \n3      8.0  67.13   20.0  ...     AU   \n4      7.0  62.70  160.0  ...     AU   \n...    ...    ...    ...  ...    ...   \n6425   9.0  81.87   10.0  ...     ZA   \n6426   6.0  51.46   60.0  ...     ZA   \n6427   6.0  76.17   40.0  ...     ZA   \n6428   7.0  93.40  120.0  ...     ZA   \n6429   6.0  71.26  120.0  ...     ZA   \n\n                                               geometry           name  \\\n0     [1, 1, 0, 0, 0, 129, 38, 194, 134, 167, 23, 10...     Queenstown   \n1     [1, 1, 0, 0, 0, 129, 38, 194, 134, 167, 23, 10...     Queenstown   \n2     [1, 1, 0, 0, 0, 240, 133, 201, 84, 193, 22, 99...       Amberley   \n3     [1, 1, 0, 0, 0, 10, 104, 34, 108, 120, 254, 92...          Perth   \n4     [1, 1, 0, 0, 0, 156, 196, 32, 176, 114, 188, 9...  Alice Springs   \n...                                                 ...            ...   \n6425  [1, 1, 0, 0, 0, 51, 196, 177, 46, 110, 211, 59...    East London   \n6426  [1, 1, 0, 0, 0, 51, 51, 51, 51, 51, 227, 49, 6...      Springbok   \n6427  [1, 1, 0, 0, 0, 109, 197, 254, 178, 123, 66, 5...       Upington   \n6428  [1, 1, 0, 0, 0, 236, 81, 184, 30, 133, 171, 60...         Umtata   \n6429  [1, 1, 0, 0, 0, 97, 195, 211, 43, 101, 57, 60,...       Pretoria   \n\n      elevation  country  county  wfo               tzname  \\\n0         356.0       AU     NaN  NaN     Pacific/Auckland   \n1         356.0       AU     NaN  NaN     Pacific/Auckland   \n2          28.0       AU     NaN  NaN   Australia/Brisbane   \n3          13.0       AU     NaN  NaN      Australia/Perth   \n4         541.0       AU     NaN  NaN     Australia/Darwin   \n...         ...      ...     ...  ...                  ...   \n6425      125.0       ZA     NaN  NaN  Africa/Johannesburg   \n6426      990.0       ZA     NaN  NaN  Africa/Johannesburg   \n6427      836.0       ZA     NaN  NaN  Africa/Johannesburg   \n6428      752.0       ZA     NaN  NaN  Africa/Johannesburg   \n6429     1248.0       ZA     NaN  NaN  Africa/Johannesburg   \n\n                                                   bbox  year  \n0     {'xmin': 168.7392, 'ymin': -45.0211, 'xmax': 1...  2026  \n1     {'xmin': 168.7392, 'ymin': -45.0211, 'xmax': 1...  2026  \n2     {'xmin': 152.7111, 'ymin': -27.6297, 'xmax': 1...  2026  \n3     {'xmin': 115.9761, 'ymin': -31.9275, 'xmax': 1...  2026  \n4     {'xmin': 133.889, 'ymin': -23.7951, 'xmax': 13...  2026  \n...                                                 ...   ...  \n6425  {'xmin': 27.8259, 'ymin': -33.0356, 'xmax': 27...  2026  \n6426  {'xmin': 17.8875, 'ymin': -29.6719, 'xmax': 17...  2026  \n6427  {'xmin': 21.2597, 'ymin': -28.4136, 'xmax': 21...  2026  \n6428  {'xmin': 28.67, 'ymin': -31.53, 'xmax': 28.67,...  2026  \n6429  {'xmin': 28.2242, 'ymin': -25.6539, 'xmax': 28...  2026  \n\n[6430 rows x 27 columns]","content_type":"text/plain"},"text/html":{"content":"<div>\n<style scoped>\n    .dataframe tbody tr th:only-of-type {\n        vertical-align: middle;\n    }\n\n    .dataframe tbody tr th {\n        vertical-align: top;\n    }\n\n    .dataframe thead th {\n        text-align: right;\n    }\n</style>\n<table border=\"1\" class=\"dataframe\">\n  <thead>\n    <tr style=\"text-align: right;\">\n      <th></th>\n      <th>station</th>\n      <th>valid</th>\n      <th>longitude</th>\n      <th>latitude</th>\n      <th>tmpf</th>\n      <th>tmpc</th>\n      <th>dwpf</th>\n      <th>dwpc</th>\n      <th>relh</th>\n      <th>drct</th>\n      <th>...</th>\n      <th>state</th>\n      <th>geometry</th>\n      <th>name</th>\n      <th>elevation</th>\n      <th>country</th>\n      <th>county</th>\n      <th>wfo</th>\n      <th>tzname</th>\n      <th>bbox</th>\n      <th>year</th>\n    </tr>\n  </thead>\n  <tbody>\n    <tr>\n      <th>0</th>\n      <td>NZQN</td>\n      <td>2026-06-20 02:30:00+00:00</td>\n      <td>168.7392</td>\n      <td>-45.0211</td>\n      <td>51.8</td>\n      <td>11.0</td>\n      <td>50.0</td>\n      <td>10.0</td>\n      <td>93.55</td>\n      <td>250.0</td>\n      <td>...</td>\n      <td>AU</td>\n      <td>[1, 1, 0, 0, 0, 129, 38, 194, 134, 167, 23, 10...</td>\n      <td>Queenstown</td>\n      <td>356.0</td>\n      <td>AU</td>\n      <td>NaN</td>\n      <td>NaN</td>\n      <td>Pacific/Auckland</td>\n      <td>{'xmin': 168.7392, 'ymin': -45.0211, 'xmax': 1...</td>\n      <td>2026</td>\n    </tr>\n    <tr>\n      <th>1</th>\n      <td>NZQN</td>\n      <td>2026-06-20 03:00:00+00:00</td>\n      <td>168.7392</td>\n      <td>-45.0211</td>\n      <td>51.8</td>\n      <td>11.0</td>\n      <td>50.0</td>\n      <td>10.0</td>\n      <td>93.55</td>\n      <td>250.0</td>\n      <td>...</td>\n      <td>AU</td>\n      <td>[1, 1, 0, 0, 0, 129, 38, 194, 134, 167, 23, 10...</td>\n      <td>Queenstown</td>\n      <td>356.0</td>\n      <td>AU</td>\n      <td>NaN</td>\n      <td>NaN</td>\n      <td>Pacific/Auckland</td>\n      <td>{'xmin': 168.7392, 'ymin': -45.0211, 'xmax': 1...</td>\n      <td>2026</td>\n    </tr>\n    <tr>\n      <th>2</th>\n      <td>YAMB</td>\n      <td>2026-06-20 02:30:00+00:00</td>\n      <td>152.7111</td>\n      <td>-27.6297</td>\n      <td>75.2</td>\n      <td>24.0</td>\n      <td>55.4</td>\n      <td>13.0</td>\n      <td>50.22</td>\n      <td>320.0</td>\n      <td>...</td>\n      <td>AU</td>\n      <td>[1, 1, 0, 0, 0, 240, 133, 201, 84, 193, 22, 99...</td>\n      <td>Amberley</td>\n      <td>28.0</td>\n      <td>AU</td>\n      <td>NaN</td>\n      <td>NaN</td>\n      <td>Australia/Brisbane</td>\n      <td>{'xmin': 152.7111, 'ymin': -27.6297, 'xmax': 1...</td>\n      <td>2026</td>\n    </tr>\n    <tr>\n      <th>3</th>\n      <td>YPPH</td>\n      <td>2026-06-20 02:30:00+00:00</td>\n      <td>115.9761</td>\n      <td>-31.9275</td>\n      <td>57.2</td>\n      <td>14.0</td>\n      <td>46.4</td>\n      <td>8.0</td>\n      <td>67.13</td>\n      <td>20.0</td>\n      <td>...</td>\n      <td>AU</td>\n      <td>[1, 1, 0, 0, 0, 10, 104, 34, 108, 120, 254, 92...</td>\n      <td>Perth</td>\n      <td>13.0</td>\n      <td>AU</td>\n      <td>NaN</td>\n      <td>NaN</td>\n      <td>Australia/Perth</td>\n      <td>{'xmin': 115.9761, 'ymin': -31.9275, 'xmax': 1...</td>\n      <td>2026</td>\n    </tr>\n    <tr>\n      <th>4</th>\n      <td>YBAS</td>\n      <td>2026-06-20 02:30:00+00:00</td>\n      <td>133.8890</td>\n      <td>-23.7951</td>\n      <td>57.2</td>\n      <td>14.0</td>\n      <td>44.6</td>\n      <td>7.0</td>\n      <td>62.70</td>\n      <td>160.0</td>\n      <td>...</td>\n      <td>AU</td>\n      <td>[1, 1, 0, 0, 0, 156, 196, 32, 176, 114, 188, 9...</td>\n      <td>Alice Springs</td>\n      <td>541.0</td>\n      <td>AU</td>\n      <td>NaN</td>\n      <td>NaN</td>\n      <td>Australia/Darwin</td>\n      <td>{'xmin': 133.889, 'ymin': -23.7951, 'xmax': 13...</td>\n      <td>2026</td>\n    </tr>\n    <tr>\n      <th>...</th>\n      <td>...</td>\n      <td>...</td>\n      <td>...</td>\n      <td>...</td>\n      <td>...</td>\n      <td>...</td>\n      <td>...</td>\n      <td>...</td>\n      <td>...</td>\n      <td>...</td>\n      <td>...</td>\n      <td>...</td>\n      <td>...</td>\n      <td>...</td>\n      <td>...</td>\n      <td>...</td>\n      <td>...</td>\n      <td>...</td>\n      <td>...</td>\n      <td>...</td>\n      <td>...</td>\n    </tr>\n    <tr>\n      <th>6425</th>\n      <td>FAEL</td>\n      <td>2026-06-20 03:00:00+00:00</td>\n      <td>27.8259</td>\n      <td>-33.0356</td>\n      <td>53.6</td>\n      <td>12.0</td>\n      <td>48.2</td>\n      <td>9.0</td>\n      <td>81.87</td>\n      <td>10.0</td>\n      <td>...</td>\n      <td>ZA</td>\n      <td>[1, 1, 0, 0, 0, 51, 196, 177, 46, 110, 211, 59...</td>\n      <td>East London</td>\n      <td>125.0</td>\n      <td>ZA</td>\n      <td>NaN</td>\n      <td>NaN</td>\n      <td>Africa/Johannesburg</td>\n      <td>{'xmin': 27.8259, 'ymin': -33.0356, 'xmax': 27...</td>\n      <td>2026</td>\n    </tr>\n    <tr>\n      <th>6426</th>\n      <td>FASB</td>\n      <td>2026-06-20 02:55:00+00:00</td>\n      <td>17.8875</td>\n      <td>-29.6719</td>\n      <td>60.8</td>\n      <td>16.0</td>\n      <td>42.8</td>\n      <td>6.0</td>\n      <td>51.46</td>\n      <td>60.0</td>\n      <td>...</td>\n      <td>ZA</td>\n      <td>[1, 1, 0, 0, 0, 51, 51, 51, 51, 51, 227, 49, 6...</td>\n      <td>Springbok</td>\n      <td>990.0</td>\n      <td>ZA</td>\n      <td>NaN</td>\n      <td>NaN</td>\n      <td>Africa/Johannesburg</td>\n      <td>{'xmin': 17.8875, 'ymin': -29.6719, 'xmax': 17...</td>\n      <td>2026</td>\n    </tr>\n    <tr>\n      <th>6427</th>\n      <td>FAUP</td>\n      <td>2026-06-20 03:00:00+00:00</td>\n      <td>21.2597</td>\n      <td>-28.4136</td>\n      <td>50.0</td>\n      <td>10.0</td>\n      <td>42.8</td>\n      <td>6.0</td>\n      <td>76.17</td>\n      <td>40.0</td>\n      <td>...</td>\n      <td>ZA</td>\n      <td>[1, 1, 0, 0, 0, 109, 197, 254, 178, 123, 66, 5...</td>\n      <td>Upington</td>\n      <td>836.0</td>\n      <td>ZA</td>\n      <td>NaN</td>\n      <td>NaN</td>\n      <td>Africa/Johannesburg</td>\n      <td>{'xmin': 21.2597, 'ymin': -28.4136, 'xmax': 21...</td>\n      <td>2026</td>\n    </tr>\n    <tr>\n      <th>6428</th>\n      <td>FAUT</td>\n      <td>2026-06-20 03:00:00+00:00</td>\n      <td>28.6700</td>\n      <td>-31.5300</td>\n      <td>46.4</td>\n      <td>8.0</td>\n      <td>44.6</td>\n      <td>7.0</td>\n      <td>93.40</td>\n      <td>120.0</td>\n      <td>...</td>\n      <td>ZA</td>\n      <td>[1, 1, 0, 0, 0, 236, 81, 184, 30, 133, 171, 60...</td>\n      <td>Umtata</td>\n      <td>752.0</td>\n      <td>ZA</td>\n      <td>NaN</td>\n      <td>NaN</td>\n      <td>Africa/Johannesburg</td>\n      <td>{'xmin': 28.67, 'ymin': -31.53, 'xmax': 28.67,...</td>\n      <td>2026</td>\n    </tr>\n    <tr>\n      <th>6429</th>\n      <td>FAWB</td>\n      <td>2026-06-20 03:00:00+00:00</td>\n      <td>28.2242</td>\n      <td>-25.6539</td>\n      <td>51.8</td>\n      <td>11.0</td>\n      <td>42.8</td>\n      <td>6.0</td>\n      <td>71.26</td>\n      <td>120.0</td>\n      <td>...</td>\n      <td>ZA</td>\n      <td>[1, 1, 0, 0, 0, 97, 195, 211, 43, 101, 57, 60,...</td>\n      <td>Pretoria</td>\n      <td>1248.0</td>\n      <td>ZA</td>\n      <td>NaN</td>\n      <td>NaN</td>\n      <td>Africa/Johannesburg</td>\n      <td>{'xmin': 28.2242, 'ymin': -25.6539, 'xmax': 28...</td>\n      <td>2026</td>\n    </tr>\n  </tbody>\n</table>\n<p>6430 rows × 27 columns</p>\n</div>","content_type":"text/html"}}},"key":"Yaea5icqn2"}],"key":"B72iTBToDP"}],"key":"K9f79ISjY3"},{"type":"block","kind":"notebook-code","children":[{"type":"code","lang":"python","executable":true,"value":"gdf = gpd.GeoDataFrame(df,geometry=gpd.points_from_xy(df.longitude,df.latitude))","key":"MzndvuLOlL"},{"type":"outputs","id":"c-fkt6SZ5mQRzGudaj-Wb","children":[],"key":"PvJ5zmbJ8N"}],"key":"HE1doA7umQ"},{"type":"block","kind":"notebook-code","children":[{"type":"code","lang":"python","executable":true,"value":"gdf.explore()","key":"q0omjed0Sq"},{"type":"outputs","id":"FAJ4wGeTajgV1O4sqt-W1","children":[{"type":"output","children":[],"jupyter_data":{"output_type":"execute_result","execution_count":9,"metadata":{},"data":{"text/plain":{"content":"<folium.folium.Map at 0x7f05bfc167b0>","content_type":"text/plain"},"text/html":{"content_type":"text/html","hash":"d58a6d6feb241a514e0a29593778be8e","path":"/METAR_archive-cookbook/build/d58a6d6feb241a514e0a29593778be8e.html"}}},"key":"Tr61t5l3yj"}],"key":"vCFZJzj4aM"}],"key":"eksq1smk7e"},{"type":"block","kind":"notebook-content","children":[{"type":"admonition","kind":"warning","children":[{"type":"admonitionTitle","children":[{"type":"text","value":"Where are the cartographic features?","position":{"start":{"line":1,"column":1},"end":{"line":1,"column":1}},"key":"OlsRKCESkm"}],"key":"ymJv8rzswK"},{"type":"paragraph","position":{"start":{"line":2,"column":1},"end":{"line":2,"column":1}},"children":[{"type":"text","value":"Well … we have an interactive frame … and we can infer worldwide geography from it  … but where are the cartographic features??","position":{"start":{"line":2,"column":1},"end":{"line":2,"column":1}},"key":"l4f7IKmbzq"}],"key":"FW0QIbjjf6"},{"type":"paragraph","position":{"start":{"line":4,"column":1},"end":{"line":4,"column":1}},"children":[{"type":"text","value":"We still have a little more work to do:","position":{"start":{"line":4,"column":1},"end":{"line":4,"column":1}},"key":"elEbhKXvww"}],"key":"Vq4hCiIWK0"},{"type":"paragraph","position":{"start":{"line":6,"column":1},"end":{"line":6,"column":1}},"children":[{"type":"text","value":"While the points certainly look like latitude and longitudes, we need to explicitly assign a projection to the Dataframe before we can view it on a map. One way is to assign a coordinate reference system code, via ","position":{"start":{"line":6,"column":1},"end":{"line":6,"column":1}},"key":"i5QKOoy4A8"},{"type":"link","url":"https://epsg.io","position":{"start":{"line":6,"column":1},"end":{"line":6,"column":1}},"children":[{"type":"text","value":"EPSG","position":{"start":{"line":6,"column":1},"end":{"line":6,"column":1}},"key":"s4j2XP9zUd"}],"urlSource":"https://epsg.io","key":"u1AqdVDX3R"},{"type":"text","value":" … in this case, EPSG 4326.","position":{"start":{"line":6,"column":1},"end":{"line":6,"column":1}},"key":"WFG4XunQDJ"}],"key":"pb3ZNWVJPB"},{"type":"paragraph","position":{"start":{"line":8,"column":1},"end":{"line":8,"column":1}},"children":[{"type":"text","value":"Note the arguments to ","position":{"start":{"line":8,"column":1},"end":{"line":8,"column":1}},"key":"ncqU8DIHLN"},{"type":"inlineCode","value":"set_crs","position":{"start":{"line":8,"column":1},"end":{"line":8,"column":1}},"key":"EDPG60hA5o"},{"type":"text","value":":","position":{"start":{"line":8,"column":1},"end":{"line":8,"column":1}},"key":"ikC4O79N5m"}],"key":"CeCA39jxZ6"},{"type":"paragraph","position":{"start":{"line":10,"column":1},"end":{"line":10,"column":1}},"children":[{"type":"inlineCode","value":"epsg = 4326","position":{"start":{"line":10,"column":1},"end":{"line":10,"column":1}},"key":"dwR9jtzv2H"},{"type":"text","value":": Assign the specified CRS","position":{"start":{"line":10,"column":1},"end":{"line":10,"column":1}},"key":"xMJRrNTSNR"}],"key":"HACfuiHiJF"},{"type":"paragraph","position":{"start":{"line":12,"column":1},"end":{"line":12,"column":1}},"children":[{"type":"inlineCode","value":"inplace = True","position":{"start":{"line":12,"column":1},"end":{"line":12,"column":1}},"key":"m5lWp44ly9"},{"type":"text","value":": The gdf object is updated without the need to assign a new dataframe object","position":{"start":{"line":12,"column":1},"end":{"line":12,"column":1}},"key":"eDGPdtptrD"}],"key":"OE4x5s8Fbn"},{"type":"paragraph","position":{"start":{"line":14,"column":1},"end":{"line":14,"column":1}},"children":[{"type":"inlineCode","value":"allow_override","position":{"start":{"line":14,"column":1},"end":{"line":14,"column":1}},"key":"wkBcasgQ6x"},{"type":"text","value":" = True: If a CRS had previously been applied, override with the EPSG value specified.","position":{"start":{"line":14,"column":1},"end":{"line":14,"column":1}},"key":"apTeYO7Pan"}],"key":"LX9opSLauK"}],"key":"atVohStL1y"}],"key":"Dxnvwvn3uW"},{"type":"block","kind":"notebook-code","children":[{"type":"code","lang":"python","executable":true,"value":"gdf.set_crs(epsg=4326, inplace=True, allow_override=True)","key":"qDcm3vP0JK"},{"type":"outputs","id":"QUC2WvcYcq0wxXyU4QGTn","children":[{"type":"output","children":[],"jupyter_data":{"output_type":"execute_result","execution_count":10,"metadata":{},"data":{"text/plain":{"content":"     station                     valid  longitude  latitude  tmpf  tmpc  dwpf  \\\n0       NZQN 2026-06-20 02:30:00+00:00   168.7392  -45.0211  51.8  11.0  50.0   \n1       NZQN 2026-06-20 03:00:00+00:00   168.7392  -45.0211  51.8  11.0  50.0   \n2       YAMB 2026-06-20 02:30:00+00:00   152.7111  -27.6297  75.2  24.0  55.4   \n3       YPPH 2026-06-20 02:30:00+00:00   115.9761  -31.9275  57.2  14.0  46.4   \n4       YBAS 2026-06-20 02:30:00+00:00   133.8890  -23.7951  57.2  14.0  44.6   \n...      ...                       ...        ...       ...   ...   ...   ...   \n6425    FAEL 2026-06-20 03:00:00+00:00    27.8259  -33.0356  53.6  12.0  48.2   \n6426    FASB 2026-06-20 02:55:00+00:00    17.8875  -29.6719  60.8  16.0  42.8   \n6427    FAUP 2026-06-20 03:00:00+00:00    21.2597  -28.4136  50.0  10.0  42.8   \n6428    FAUT 2026-06-20 03:00:00+00:00    28.6700  -31.5300  46.4   8.0  44.6   \n6429    FAWB 2026-06-20 03:00:00+00:00    28.2242  -25.6539  51.8  11.0  42.8   \n\n      dwpc   relh   drct  ...  state                   geometry  \\\n0     10.0  93.55  250.0  ...     AU  POINT (168.7392 -45.0211)   \n1     10.0  93.55  250.0  ...     AU  POINT (168.7392 -45.0211)   \n2     13.0  50.22  320.0  ...     AU  POINT (152.7111 -27.6297)   \n3      8.0  67.13   20.0  ...     AU  POINT (115.9761 -31.9275)   \n4      7.0  62.70  160.0  ...     AU   POINT (133.889 -23.7951)   \n...    ...    ...    ...  ...    ...                        ...   \n6425   9.0  81.87   10.0  ...     ZA   POINT (27.8259 -33.0356)   \n6426   6.0  51.46   60.0  ...     ZA   POINT (17.8875 -29.6719)   \n6427   6.0  76.17   40.0  ...     ZA   POINT (21.2597 -28.4136)   \n6428   7.0  93.40  120.0  ...     ZA       POINT (28.67 -31.53)   \n6429   6.0  71.26  120.0  ...     ZA   POINT (28.2242 -25.6539)   \n\n               name  elevation  country  county  wfo               tzname  \\\n0        Queenstown      356.0       AU     NaN  NaN     Pacific/Auckland   \n1        Queenstown      356.0       AU     NaN  NaN     Pacific/Auckland   \n2          Amberley       28.0       AU     NaN  NaN   Australia/Brisbane   \n3             Perth       13.0       AU     NaN  NaN      Australia/Perth   \n4     Alice Springs      541.0       AU     NaN  NaN     Australia/Darwin   \n...             ...        ...      ...     ...  ...                  ...   \n6425    East London      125.0       ZA     NaN  NaN  Africa/Johannesburg   \n6426      Springbok      990.0       ZA     NaN  NaN  Africa/Johannesburg   \n6427       Upington      836.0       ZA     NaN  NaN  Africa/Johannesburg   \n6428         Umtata      752.0       ZA     NaN  NaN  Africa/Johannesburg   \n6429       Pretoria     1248.0       ZA     NaN  NaN  Africa/Johannesburg   \n\n                                                   bbox  year  \n0     {'xmin': 168.7392, 'ymin': -45.0211, 'xmax': 1...  2026  \n1     {'xmin': 168.7392, 'ymin': -45.0211, 'xmax': 1...  2026  \n2     {'xmin': 152.7111, 'ymin': -27.6297, 'xmax': 1...  2026  \n3     {'xmin': 115.9761, 'ymin': -31.9275, 'xmax': 1...  2026  \n4     {'xmin': 133.889, 'ymin': -23.7951, 'xmax': 13...  2026  \n...                                                 ...   ...  \n6425  {'xmin': 27.8259, 'ymin': -33.0356, 'xmax': 27...  2026  \n6426  {'xmin': 17.8875, 'ymin': -29.6719, 'xmax': 17...  2026  \n6427  {'xmin': 21.2597, 'ymin': -28.4136, 'xmax': 21...  2026  \n6428  {'xmin': 28.67, 'ymin': -31.53, 'xmax': 28.67,...  2026  \n6429  {'xmin': 28.2242, 'ymin': -25.6539, 'xmax': 28...  2026  \n\n[6430 rows x 27 columns]","content_type":"text/plain"},"text/html":{"content":"<div>\n<style scoped>\n    .dataframe tbody tr th:only-of-type {\n        vertical-align: middle;\n    }\n\n    .dataframe tbody tr th {\n        vertical-align: top;\n    }\n\n    .dataframe thead th {\n        text-align: right;\n    }\n</style>\n<table border=\"1\" class=\"dataframe\">\n  <thead>\n    <tr style=\"text-align: right;\">\n      <th></th>\n      <th>station</th>\n      <th>valid</th>\n      <th>longitude</th>\n      <th>latitude</th>\n      <th>tmpf</th>\n      <th>tmpc</th>\n      <th>dwpf</th>\n      <th>dwpc</th>\n      <th>relh</th>\n      <th>drct</th>\n      <th>...</th>\n      <th>state</th>\n      <th>geometry</th>\n      <th>name</th>\n      <th>elevation</th>\n      <th>country</th>\n      <th>county</th>\n      <th>wfo</th>\n      <th>tzname</th>\n      <th>bbox</th>\n      <th>year</th>\n    </tr>\n  </thead>\n  <tbody>\n    <tr>\n      <th>0</th>\n      <td>NZQN</td>\n      <td>2026-06-20 02:30:00+00:00</td>\n      <td>168.7392</td>\n      <td>-45.0211</td>\n      <td>51.8</td>\n      <td>11.0</td>\n      <td>50.0</td>\n      <td>10.0</td>\n      <td>93.55</td>\n      <td>250.0</td>\n      <td>...</td>\n      <td>AU</td>\n      <td>POINT (168.7392 -45.0211)</td>\n      <td>Queenstown</td>\n      <td>356.0</td>\n      <td>AU</td>\n      <td>NaN</td>\n      <td>NaN</td>\n      <td>Pacific/Auckland</td>\n      <td>{'xmin': 168.7392, 'ymin': -45.0211, 'xmax': 1...</td>\n      <td>2026</td>\n    </tr>\n    <tr>\n      <th>1</th>\n      <td>NZQN</td>\n      <td>2026-06-20 03:00:00+00:00</td>\n      <td>168.7392</td>\n      <td>-45.0211</td>\n      <td>51.8</td>\n      <td>11.0</td>\n      <td>50.0</td>\n      <td>10.0</td>\n      <td>93.55</td>\n      <td>250.0</td>\n      <td>...</td>\n      <td>AU</td>\n      <td>POINT (168.7392 -45.0211)</td>\n      <td>Queenstown</td>\n      <td>356.0</td>\n      <td>AU</td>\n      <td>NaN</td>\n      <td>NaN</td>\n      <td>Pacific/Auckland</td>\n      <td>{'xmin': 168.7392, 'ymin': -45.0211, 'xmax': 1...</td>\n      <td>2026</td>\n    </tr>\n    <tr>\n      <th>2</th>\n      <td>YAMB</td>\n      <td>2026-06-20 02:30:00+00:00</td>\n      <td>152.7111</td>\n      <td>-27.6297</td>\n      <td>75.2</td>\n      <td>24.0</td>\n      <td>55.4</td>\n      <td>13.0</td>\n      <td>50.22</td>\n      <td>320.0</td>\n      <td>...</td>\n      <td>AU</td>\n      <td>POINT (152.7111 -27.6297)</td>\n      <td>Amberley</td>\n      <td>28.0</td>\n      <td>AU</td>\n      <td>NaN</td>\n      <td>NaN</td>\n      <td>Australia/Brisbane</td>\n      <td>{'xmin': 152.7111, 'ymin': -27.6297, 'xmax': 1...</td>\n      <td>2026</td>\n    </tr>\n    <tr>\n      <th>3</th>\n      <td>YPPH</td>\n      <td>2026-06-20 02:30:00+00:00</td>\n      <td>115.9761</td>\n      <td>-31.9275</td>\n      <td>57.2</td>\n      <td>14.0</td>\n      <td>46.4</td>\n      <td>8.0</td>\n      <td>67.13</td>\n      <td>20.0</td>\n      <td>...</td>\n      <td>AU</td>\n      <td>POINT (115.9761 -31.9275)</td>\n      <td>Perth</td>\n      <td>13.0</td>\n      <td>AU</td>\n      <td>NaN</td>\n      <td>NaN</td>\n      <td>Australia/Perth</td>\n      <td>{'xmin': 115.9761, 'ymin': -31.9275, 'xmax': 1...</td>\n      <td>2026</td>\n    </tr>\n    <tr>\n      <th>4</th>\n      <td>YBAS</td>\n      <td>2026-06-20 02:30:00+00:00</td>\n      <td>133.8890</td>\n      <td>-23.7951</td>\n      <td>57.2</td>\n      <td>14.0</td>\n      <td>44.6</td>\n      <td>7.0</td>\n      <td>62.70</td>\n      <td>160.0</td>\n      <td>...</td>\n      <td>AU</td>\n      <td>POINT (133.889 -23.7951)</td>\n      <td>Alice Springs</td>\n      <td>541.0</td>\n      <td>AU</td>\n      <td>NaN</td>\n      <td>NaN</td>\n      <td>Australia/Darwin</td>\n      <td>{'xmin': 133.889, 'ymin': -23.7951, 'xmax': 13...</td>\n      <td>2026</td>\n    </tr>\n    <tr>\n      <th>...</th>\n      <td>...</td>\n      <td>...</td>\n      <td>...</td>\n      <td>...</td>\n      <td>...</td>\n      <td>...</td>\n      <td>...</td>\n      <td>...</td>\n      <td>...</td>\n      <td>...</td>\n      <td>...</td>\n      <td>...</td>\n      <td>...</td>\n      <td>...</td>\n      <td>...</td>\n      <td>...</td>\n      <td>...</td>\n      <td>...</td>\n      <td>...</td>\n      <td>...</td>\n      <td>...</td>\n    </tr>\n    <tr>\n      <th>6425</th>\n      <td>FAEL</td>\n      <td>2026-06-20 03:00:00+00:00</td>\n      <td>27.8259</td>\n      <td>-33.0356</td>\n      <td>53.6</td>\n      <td>12.0</td>\n      <td>48.2</td>\n      <td>9.0</td>\n      <td>81.87</td>\n      <td>10.0</td>\n      <td>...</td>\n      <td>ZA</td>\n      <td>POINT (27.8259 -33.0356)</td>\n      <td>East London</td>\n      <td>125.0</td>\n      <td>ZA</td>\n      <td>NaN</td>\n      <td>NaN</td>\n      <td>Africa/Johannesburg</td>\n      <td>{'xmin': 27.8259, 'ymin': -33.0356, 'xmax': 27...</td>\n      <td>2026</td>\n    </tr>\n    <tr>\n      <th>6426</th>\n      <td>FASB</td>\n      <td>2026-06-20 02:55:00+00:00</td>\n      <td>17.8875</td>\n      <td>-29.6719</td>\n      <td>60.8</td>\n      <td>16.0</td>\n      <td>42.8</td>\n      <td>6.0</td>\n      <td>51.46</td>\n      <td>60.0</td>\n      <td>...</td>\n      <td>ZA</td>\n      <td>POINT (17.8875 -29.6719)</td>\n      <td>Springbok</td>\n      <td>990.0</td>\n      <td>ZA</td>\n      <td>NaN</td>\n      <td>NaN</td>\n      <td>Africa/Johannesburg</td>\n      <td>{'xmin': 17.8875, 'ymin': -29.6719, 'xmax': 17...</td>\n      <td>2026</td>\n    </tr>\n    <tr>\n      <th>6427</th>\n      <td>FAUP</td>\n      <td>2026-06-20 03:00:00+00:00</td>\n      <td>21.2597</td>\n      <td>-28.4136</td>\n      <td>50.0</td>\n      <td>10.0</td>\n      <td>42.8</td>\n      <td>6.0</td>\n      <td>76.17</td>\n      <td>40.0</td>\n      <td>...</td>\n      <td>ZA</td>\n      <td>POINT (21.2597 -28.4136)</td>\n      <td>Upington</td>\n      <td>836.0</td>\n      <td>ZA</td>\n      <td>NaN</td>\n      <td>NaN</td>\n      <td>Africa/Johannesburg</td>\n      <td>{'xmin': 21.2597, 'ymin': -28.4136, 'xmax': 21...</td>\n      <td>2026</td>\n    </tr>\n    <tr>\n      <th>6428</th>\n      <td>FAUT</td>\n      <td>2026-06-20 03:00:00+00:00</td>\n      <td>28.6700</td>\n      <td>-31.5300</td>\n      <td>46.4</td>\n      <td>8.0</td>\n      <td>44.6</td>\n      <td>7.0</td>\n      <td>93.40</td>\n      <td>120.0</td>\n      <td>...</td>\n      <td>ZA</td>\n      <td>POINT (28.67 -31.53)</td>\n      <td>Umtata</td>\n      <td>752.0</td>\n      <td>ZA</td>\n      <td>NaN</td>\n      <td>NaN</td>\n      <td>Africa/Johannesburg</td>\n      <td>{'xmin': 28.67, 'ymin': -31.53, 'xmax': 28.67,...</td>\n      <td>2026</td>\n    </tr>\n    <tr>\n      <th>6429</th>\n      <td>FAWB</td>\n      <td>2026-06-20 03:00:00+00:00</td>\n      <td>28.2242</td>\n      <td>-25.6539</td>\n      <td>51.8</td>\n      <td>11.0</td>\n      <td>42.8</td>\n      <td>6.0</td>\n      <td>71.26</td>\n      <td>120.0</td>\n      <td>...</td>\n      <td>ZA</td>\n      <td>POINT (28.2242 -25.6539)</td>\n      <td>Pretoria</td>\n      <td>1248.0</td>\n      <td>ZA</td>\n      <td>NaN</td>\n      <td>NaN</td>\n      <td>Africa/Johannesburg</td>\n      <td>{'xmin': 28.2242, 'ymin': -25.6539, 'xmax': 28...</td>\n      <td>2026</td>\n    </tr>\n  </tbody>\n</table>\n<p>6430 rows × 27 columns</p>\n</div>","content_type":"text/html"}}},"key":"SqyWDuD3kX"}],"key":"YeBveqXml0"}],"key":"NpY6eBJLlc"},{"type":"block","kind":"notebook-code","children":[{"type":"code","lang":"python","executable":true,"value":"gdf.explore()","key":"APwhxqx9pI"},{"type":"outputs","id":"hCVP0GwAuwX1s2PeZjV4H","children":[{"type":"output","children":[],"jupyter_data":{"output_type":"execute_result","execution_count":11,"metadata":{},"data":{"text/plain":{"content":"<folium.folium.Map at 0x7f05f8a76990>","content_type":"text/plain"},"text/html":{"content_type":"text/html","hash":"f940954e4e10a8569e010eea8bf0c3ce","path":"/METAR_archive-cookbook/build/f940954e4e10a8569e010eea8bf0c3ce.html"}}},"key":"aTMo1jN1zj"}],"key":"K6K8kpyk5Z"}],"key":"PWqSKEBBoQ"},{"type":"block","kind":"notebook-content","children":[{"type":"admonition","kind":"error","children":[{"type":"admonitionTitle","children":[{"type":"text","value":"Missing data from many countries!","position":{"start":{"line":1,"column":1},"end":{"line":1,"column":1}},"key":"FWEG16dtzH"}],"key":"wD5ULuVrAD"},{"type":"paragraph","position":{"start":{"line":2,"column":1},"end":{"line":2,"column":1}},"children":[{"type":"text","value":"It seems that many countries don’t seem to have any METAR observations (e.g., Norway, Nigeria). They definitely do exist, but the seem to not be included in this archive!","position":{"start":{"line":2,"column":1},"end":{"line":2,"column":1}},"key":"vyC5lP8jA1"}],"key":"ikI9rG8Q25"}],"key":"ffTwttOALj"}],"key":"VFUxYAB3q6"},{"type":"block","kind":"notebook-content","children":[{"type":"paragraph","position":{"start":{"line":1,"column":1},"end":{"line":1,"column":1}},"children":[{"type":"text","value":"Now, let’s choose a specific variable ... in this case, ","position":{"start":{"line":1,"column":1},"end":{"line":1,"column":1}},"key":"Tl1nU0JkCv"},{"type":"inlineCode","value":"tmpc","position":{"start":{"line":1,"column":1},"end":{"line":1,"column":1}},"key":"EA9K9qjf9h"},{"type":"text","value":" (2-meter temperature in °C)","position":{"start":{"line":1,"column":1},"end":{"line":1,"column":1}},"key":"PndLOlNUyq"}],"key":"DpZHjSeABt"}],"key":"EvVQoDqLX0"},{"type":"block","kind":"notebook-code","data":{"tags":[]},"children":[{"type":"code","lang":"python","executable":true,"value":"gdf.explore(column='tmpc')","visibility":"show","key":"jE9ZukoN53"},{"type":"outputs","id":"CIG3SVAgOPIUFX2_tv9fq","children":[{"type":"output","children":[],"jupyter_data":{"output_type":"execute_result","execution_count":12,"metadata":{},"data":{"text/plain":{"content":"<folium.folium.Map at 0x7f0552346210>","content_type":"text/plain"},"text/html":{"content_type":"text/html","hash":"3e943972a01149d874b123f6048b09b2","path":"/METAR_archive-cookbook/build/3e943972a01149d874b123f6048b09b2.html"}}},"key":"mInhhisw5s"}],"visibility":"show","key":"DZFfSKKznH"}],"visibility":"show","key":"s3zJzAgqHs"},{"type":"block","kind":"notebook-content","children":[{"type":"admonition","kind":"note","children":[{"type":"admonitionTitle","children":[{"type":"text","value":"Note","key":"awXAMklxEt"}],"key":"TVzgA3Yaop"},{"type":"paragraph","position":{"start":{"line":2,"column":1},"end":{"line":2,"column":1}},"children":[{"type":"text","value":"The color scale is unaffected by any location whose temperature value was missing ... GeoPandas “knows” to exlucde ","position":{"start":{"line":2,"column":1},"end":{"line":2,"column":1}},"key":"uz4ABl8xSO"},{"type":"inlineCode","value":"NaN","position":{"start":{"line":2,"column":1},"end":{"line":2,"column":1}},"key":"BmjH2zukv6"},{"type":"text","value":" from the range of valid values.","position":{"start":{"line":2,"column":1},"end":{"line":2,"column":1}},"key":"TnhFlr4Ib4"}],"key":"jbAVGQYzeJ"}],"key":"lEgCkQPdss"}],"key":"sk6Areg1Mi"},{"type":"block","kind":"notebook-content","data":{"tags":[]},"children":[{"type":"paragraph","position":{"start":{"line":1,"column":1},"end":{"line":1,"column":1}},"children":[{"type":"text","value":"Plot hourly precipitation","position":{"start":{"line":1,"column":1},"end":{"line":1,"column":1}},"key":"JaxXQSQ7uD"}],"key":"kuHKCKHUsG"}],"visibility":"show","key":"FUgB5w2fKR"},{"type":"block","kind":"notebook-code","data":{"tags":[]},"children":[{"type":"code","lang":"python","executable":true,"value":"gdf.explore(column='p01m')","visibility":"show","key":"Utr83JKzt7"},{"type":"outputs","id":"qd7_D6zs2lSIjKvsLno5Z","children":[{"type":"output","children":[],"jupyter_data":{"output_type":"execute_result","execution_count":13,"metadata":{},"data":{"text/plain":{"content":"<folium.folium.Map at 0x7f05bfc3f360>","content_type":"text/plain"},"text/html":{"content_type":"text/html","hash":"b0c1530838e9e7a8bfd17c14e73b84b7","path":"/METAR_archive-cookbook/build/b0c1530838e9e7a8bfd17c14e73b84b7.html"}}},"key":"jYqDoscFGp"}],"visibility":"show","key":"utjCP7qSU2"}],"visibility":"show","key":"hGxlNIv7Ot"},{"type":"block","kind":"notebook-content","children":[{"type":"admonition","kind":"note","children":[{"type":"admonitionTitle","children":[{"type":"text","value":"Note","key":"vFHf9fOwfZ"}],"key":"zMupfdNsfH"},{"type":"paragraph","position":{"start":{"line":2,"column":1},"end":{"line":2,"column":1}},"children":[{"type":"text","value":"With few exceptions, hourly precip is only provided by US stations. Any value less than 0.01 is denoted as a ","position":{"start":{"line":2,"column":1},"end":{"line":2,"column":1}},"key":"hMCrB3Groi"},{"type":"emphasis","position":{"start":{"line":2,"column":1},"end":{"line":2,"column":1}},"children":[{"type":"text","value":"trace","position":{"start":{"line":2,"column":1},"end":{"line":2,"column":1}},"key":"bqPIOAspYu"}],"key":"cRRrujifja"},{"type":"text","value":". Let’s drop all values < 0.01.","position":{"start":{"line":2,"column":1},"end":{"line":2,"column":1}},"key":"wizpYUnME0"}],"key":"HFUzxio2ou"}],"key":"nssTmmskS8"}],"key":"Km9N1Qhekg"},{"type":"block","kind":"notebook-code","children":[{"type":"code","lang":"python","executable":true,"value":"gdf.loc[gdf['p01m'] < 0.01, 'p01m'] = np.nan","key":"Pf58pVyDzg"},{"type":"outputs","id":"7cD9px7APabtDB36pKYW2","children":[],"key":"tdvqUsoQK4"}],"key":"T4YKgToz4S"},{"type":"block","kind":"notebook-code","children":[{"type":"code","lang":"python","executable":true,"value":"gdf = gdf.dropna(subset=['p01m']).reset_index(drop=True)","key":"D07bE6xw2B"},{"type":"outputs","id":"cdHktvNyEz69ye9dRekXZ","children":[],"key":"dhhV4SRwpm"}],"key":"if18xHELwa"},{"type":"block","kind":"notebook-code","children":[{"type":"code","lang":"python","executable":true,"value":"gdf.explore(column='p01m')","key":"pTHoKRpaG7"},{"type":"outputs","id":"8ZwOIBzbxqtuiT8riLJRG","children":[{"type":"output","children":[],"jupyter_data":{"output_type":"execute_result","execution_count":16,"metadata":{},"data":{"text/plain":{"content":"<folium.folium.Map at 0x7f05bfc3fa80>","content_type":"text/plain"},"text/html":{"content_type":"text/html","hash":"4fe22c98059fd93f38a1525b2976d93d","path":"/METAR_archive-cookbook/build/4fe22c98059fd93f38a1525b2976d93d.html"}}},"key":"lFVq2uYiS6"}],"key":"ERPfKTHKiw"}],"key":"grVX7U6qws"},{"type":"block","kind":"notebook-content","children":[{"type":"heading","depth":3,"position":{"start":{"line":1,"column":1},"end":{"line":1,"column":1}},"children":[{"type":"text","value":"To-do: add title to the graphics","position":{"start":{"line":1,"column":1},"end":{"line":1,"column":1}},"key":"pKMONGwVb3"}],"identifier":"to-do-add-title-to-the-graphics","label":"To-do: add title to the graphics","html_id":"to-do-add-title-to-the-graphics","implicit":true,"key":"krd7mvmsb4"}],"key":"KBu5V96EGJ"},{"type":"block","kind":"notebook-code","children":[{"type":"code","lang":"python","executable":true,"value":"m = gdf.explore()\n\n# Add title\ntitle_string = f\"Hourly Precip (mm), {date_string}\"\n\ntitle_html = f\"\"\"\n<h3 align=\"center\" style=\"font-size:20px\">\n    <b>{title_string}</b>\n</h3>\n\"\"\"\n\nm.get_root().html.add_child(folium.Element(title_html))\n\n# Save or display\n#m.save(\"map.html\")","key":"HShoqOXmRg"},{"type":"outputs","id":"hGdINHFj2hzl0JZK_BYVL","children":[{"type":"output","children":[],"jupyter_data":{"output_type":"execute_result","execution_count":17,"metadata":{},"data":{"text/plain":{"content":"<branca.element.Element at 0x7f054ea9ba50>","content_type":"text/plain"}}},"key":"yoAQ2D7ojz"}],"key":"hTrjABpjoO"}],"key":"rtbnbCdvIt"},{"type":"block","kind":"notebook-code","children":[{"type":"code","lang":"python","executable":true,"value":"m","key":"uHAqvXnosj"},{"type":"outputs","id":"9fHm5VkPMpYRtMRzRYFTH","children":[{"type":"output","children":[],"jupyter_data":{"output_type":"execute_result","execution_count":18,"metadata":{},"data":{"text/plain":{"content":"<folium.folium.Map at 0x7f05bf9e8cb0>","content_type":"text/plain"},"text/html":{"content_type":"text/html","hash":"16c67173faba66b7772354d0f97a87a2","path":"/METAR_archive-cookbook/build/16c67173faba66b7772354d0f97a87a2.html"}}},"key":"xYApAGAAAa"}],"key":"zSbk5uYcL4"}],"key":"WKIpIbNQcE"},{"type":"block","kind":"notebook-content","data":{"tags":[]},"children":[{"type":"heading","depth":2,"position":{"start":{"line":1,"column":1},"end":{"line":1,"column":1}},"children":[{"type":"text","value":"References","position":{"start":{"line":1,"column":1},"end":{"line":1,"column":1}},"key":"edidwjAAZf"}],"identifier":"references","label":"References","html_id":"references","implicit":true,"key":"nqgtiuNegw"}],"visibility":"show","key":"bKd7saeHXn"},{"type":"block","kind":"notebook-content","children":[{"type":"list","ordered":true,"start":1,"spread":false,"position":{"start":{"line":1,"column":1},"end":{"line":2,"column":1}},"children":[{"type":"listItem","spread":true,"position":{"start":{"line":1,"column":1},"end":{"line":1,"column":1}},"children":[{"type":"paragraph","children":[{"type":"link","url":"https://geopandas.org","position":{"start":{"line":1,"column":1},"end":{"line":1,"column":1}},"children":[{"type":"text","value":"GeoPandas","position":{"start":{"line":1,"column":1},"end":{"line":1,"column":1}},"key":"E0yt3XDGjJ"}],"urlSource":"https://geopandas.org","key":"o3wRMmgV14"}],"key":"wN7439vB6o"}],"key":"DPDzbWaUoV"},{"type":"listItem","spread":true,"position":{"start":{"line":2,"column":1},"end":{"line":2,"column":1}},"children":[{"type":"paragraph","children":[{"type":"link","url":"https://epsg.io","position":{"start":{"line":2,"column":1},"end":{"line":2,"column":1}},"children":[{"type":"text","value":"EPSG","position":{"start":{"line":2,"column":1},"end":{"line":2,"column":1}},"key":"ZTwjzXA8lO"}],"urlSource":"https://epsg.io","key":"xOyKIRDJFk"}],"key":"ymM4uDii0s"}],"key":"EikMD3yZbL"}],"key":"wd2v43mcGc"}],"key":"M5f8jKxBzW"},{"type":"block","kind":"notebook-content","children":[{"type":"heading","depth":2,"position":{"start":{"line":1,"column":1},"end":{"line":1,"column":1}},"children":[{"type":"text","value":"What’s next?","position":{"start":{"line":1,"column":1},"end":{"line":1,"column":1}},"key":"BWyuMfS17p"}],"identifier":"whats-next","label":"What’s next?","html_id":"whats-next","implicit":true,"key":"U440LCco1N"},{"type":"paragraph","position":{"start":{"line":2,"column":1},"end":{"line":2,"column":1}},"children":[{"type":"text","value":"We will use ","position":{"start":{"line":2,"column":1},"end":{"line":2,"column":1}},"key":"aijwRdL40F"},{"type":"link","url":"https://developmentseed.org/lonboard/latest/","position":{"start":{"line":2,"column":1},"end":{"line":2,"column":1}},"children":[{"type":"text","value":"Lonboard","position":{"start":{"line":2,"column":1},"end":{"line":2,"column":1}},"key":"Gk4DhcfufD"}],"urlSource":"https://developmentseed.org/lonboard/latest/","key":"lZxSaNYvbu"},{"type":"text","value":" as an additional interactive visualization tool.","position":{"start":{"line":2,"column":1},"end":{"line":2,"column":1}},"key":"Zfsb3fQpAe"}],"key":"wtFtxWWpHR"}],"key":"xyi7XOxHKH"}],"key":"gnF54EKZEI"},"references":{"cite":{"order":[],"data":{}}},"footer":{"navigation":{"prev":{"title":"Surface map of METAR data","url":"/notebooks/metpy-metar-map","group":"Examples"},"next":{"title":"METAR Temperature Visualization with Lonboard","url":"/notebooks/lonboard-visualization","group":"Examples"}}},"domain":"http://localhost:3000"}